aat2/fa.v
module fa (
    input a,b,clk,rst,
    output reg [4:0]op
);

//reg c;
reg sum, carry;
integer count=0;

always @(posedge clk, posedge rst) begin
    if (rst) begin
        //c <= 0;
        sum<=0;
        carry<=0;
	op<=5'd0;
        // count <= 0;
        // flag<=0;
    end
    else if(count<6) begin
        sum <= a^b^carry;
        carry <= (a&b)|(b&carry)|(carry&a);
        //c <= carry;
	if(count>1) op[count-2]<=sum;
        count<=count+1;
	if(count==5) op[count-1]<=carry;
    end 
end
    
endmodule

aat2/shift_reg.v
`include "fa.v"
//`include "op.v"
module shift_reg (
    input [3:0] in_a, in_b,
    input clk,rst,
    // output reg [7:0] 
    output [4:0]op
);
integer i = 0;

reg out_a, out_b;

fa fa(.a(out_a),.b(out_b),.clk(clk),.rst(rst),.op(op));
//	.sum(sum),.carry(carry));
//op op(.sum(sum),.carry(carry),.clk(clk),.rst(rst),.op(op));
    always @(posedge clk, posedge rst) begin
        if(rst) begin
            {out_a,out_b} <= 2'b00;
            // i<=0;
        end
        else if(i<4)begin
            out_a <= in_a[i];
            out_b <= in_b[i];
            i <= i+1;
        end
    end
    
endmodule

aat2/tb_shift.v
module tb_shift;
reg [3:0] in_a, in_b;
reg clk,rst;
    // output reg [7:0] 
wire [4:0]op;

shift_reg dut(.in_a(in_a),.in_b(in_b),.clk(clk),.rst(rst),.op(op));

initial begin 
clk=0; rst=1; in_a=4'b1000; in_b=4'b1111;
#4 rst=0;
#100 $finish;
end

always #5 clk=~clk;

initial begin 
$dumpfile("shift.vcd");
$dumpvars;
end

endmodule

aat2/shift.vcd
$date
	Fri May 10 00:27:25 2024
$end
$version
	Icarus Verilog
$end
$timescale
	1s
$end
$scope module tb_shift $end
$var wire 5 ! op [4:0] $end
$var reg 1 " clk $end
$var reg 4 # in_a [3:0] $end
$var reg 4 $ in_b [3:0] $end
$var reg 1 % rst $end
$scope module dut $end
$var wire 1 " clk $end
$var wire 4 & in_a [3:0] $end
$var wire 4 ' in_b [3:0] $end
$var wire 1 % rst $end
$var wire 5 ( op [4:0] $end
$var reg 1 ) out_a $end
$var reg 1 * out_b $end
$var integer 32 + i [31:0] $end
$scope module fa $end
$var wire 1 ) a $end
$var wire 1 * b $end
$var wire 1 " clk $end
$var wire 1 % rst $end
$var reg 1 , carry $end
$var reg 5 - op [4:0] $end
$var reg 1 . sum $end
$var integer 32 / count [31:0] $end
$upscope $end
$upscope $end
$upscope $end
$enddefinitions $end
#0
$dumpvars
b0 /
0.
b0 -
0,
b0 +
0*
0)
b0 (
b1111 '
b1000 &
1%
b1111 $
b1000 #
0"
b0 !
$end
#4
0%
#5
b1 +
1*
b1 /
1"
#10
0"
#15
b10 /
1.
b10 +
1"
#20
0"
#25
b11 +
b11 /
b1 !
b1 (
b1 -
1"
#30
0"
#35
b100 /
b11 !
b11 (
b11 -
b100 +
1)
1"
#40
0"
#45
b101 /
b111 !
b111 (
b111 -
1,
0.
1"
#50
0"
#55
b10111 !
b10111 (
b10111 -
b110 /
1.
1"
